lampo_lnprototest/__init__.py
lampo_lnprototest/runner.py
lampo_lnprototest-0.0.1.dist-info/METADATA
lampo_lnprototest-0.0.1.dist-info/WHEEL
lampo_lnprototest-0.0.1.dist-info/RECORD
