Metadata-Version: 2.1
Name: lampo-lnprototest
Version: 0.0.1
Summary: lnprototest runner for lampo
Author: Vincenzo Palazzo
Author-email: vincenzopalazzodev@gmail.com
Requires-Python: >=3.8,<4.0
Classifier: Programming Language :: Python :: 3
Classifier: Programming Language :: Python :: 3.8
Classifier: Programming Language :: Python :: 3.9
Classifier: Programming Language :: Python :: 3.10
Classifier: Programming Language :: Python :: 3.11
Requires-Dist: lampo-py (==0.0.1a6)
Requires-Dist: lnprototest (>=0.0.4,<0.0.5)
Requires-Dist: python-bitcoinlib (>=0.11.2,<0.12.0)
